{
  "$defs": {
    "LogLevel": {
      "enum": [
        "Verbose",
        "Info",
        "Error",
        "Warning"
      ],
      "type": "string"
    }
  },
  "$schema": "https://json-schema.org/draft/2020-12/schema",
  "properties": {
    "level": {
      "$ref": "#/$defs/LogLevel"
    },
    "message": {
      "type": "string"
    },
    "with_time": {
      "type": [
        "boolean",
        "null"
      ]
    }
  },
  "required": [
    "level",
    "message"
  ],
  "title": "LogArguments",
  "type": "object"
}